<xml xmlns:o="urn:schemas-microsoft-com:office:office">
 <o:MainFile HRef="../tipos.htm"/>
 <o:File HRef="image293.png"/>
 <o:File HRef="image303.png"/>
 <o:File HRef="image310.png"/>
 <o:File HRef="image324.jpg"/>
 <o:File HRef="image339.jpg"/>
 <o:File HRef="image343.jpg"/>
 <o:File HRef="image354.png"/>
 <o:File HRef="image356.jpg"/>
 <o:File HRef="image3561.jpg"/>
 <o:File HRef="image359.jpg"/>
 <o:File HRef="image362.jpg"/>
 <o:File HRef="image3621.jpg"/>
 <o:File HRef="image370.jpg"/>
 <o:File HRef="image368.png"/>
 <o:File HRef="image3681.png"/>
 <o:File HRef="filelist.xml"/>
</xml>